cloudendure2/__init__.py
cloudendure2/cloudendure2.py
cloudendure2-0.0.3.dist-info/LICENSE
cloudendure2-0.0.3.dist-info/METADATA
cloudendure2-0.0.3.dist-info/WHEEL
cloudendure2-0.0.3.dist-info/top_level.txt
cloudendure2-0.0.3.dist-info/RECORD
