Metadata-Version: 2.1
Name: cloudendure2
Version: 0.0.3
Summary: A python wrapper for the CloudEndure API
Home-page: UNKNOWN
Author: Christian Mendez
License: MIT
Platform: Any
Classifier: Programming Language :: Python :: 3
Classifier: License :: OSI Approved :: MIT License
Classifier: Operating System :: OS Independent
Requires-Python: >=3.6
License-File: LICENSE
